LICENSE
MANIFEST.in
README.md
change_field_name_database_SQLite.py
datavision.py
datavision_TTY_plot.py
duplicates_database_SQLite.py
search_database_SQLite.py
setup.py
view_database_SQLite.py
datavision.egg-info/PKG-INFO
datavision.egg-info/SOURCES.txt
datavision.egg-info/dependency_links.txt
datavision.egg-info/entry_points.txt
datavision.egg-info/requires.txt
datavision.egg-info/top_level.txt