Metadata-Version: 1.0
Name: datavision
Version: 2018.1.8.2333
Summary: Python data visualisation
Home-page: https://github.com/wdbm/datavision
Author: Will Breaden Madden
Author-email: wbm@protonmail.ch
License: GPLv3
Platform: UNKNOWN
